{
    "action": {
        "reply": "الرد على الرسالة",
        "forward": "اعاده توجيهها",
        "copy": "نسخ",
        "delete": "حذف",
        "edit": "تعديل",
        "resetLink": "رابط إعادة تعيين",
        "activateNotifications": "تفعيل الإشعارات",
        "add": "أضف",
        "addChannel": "أضف قناة",
        "addMembers": "أضف عضو",
        "addModerator": "أضف مشرف",
        "addModerators": "أضف مشرفين",
        "copyLinkRoom": "نسخ رابط الغرفة",
        "copyLinkVirtualRoom": "نسخ رابط الغرفة الافتراضية",
        "copyUserRoomLink": "نسخ الرابط",
        "addNewMembers": "أضف أعضاء جدد",
        "addNewMembersTo": "أضف أعضاء جدد إلى",
        "addOtherModerators": "أضف مشرفين آخرين",
        "browse": "تصفح",
        "clearHistory": "مسح التاريخ",
        "close": "أغلق",
        "collapse": "طوي",
        "copyAppVersion": "نسخ نسخة التطبيق",
        "create": "أنشئ",
        "createChannel": "أنشئ قناة مرتبطة بـ{{spaceName}}",
        "createChat": "أنشئ دردشة",
        "createGroup": "أنشئ مجموعة",
        "createInstantMeeting": "أنشئ اجتماع فوري",
        "createRoom": "أنشئ غرفة",
        "createSpace": "أنشئ مساحة",
        "createVirtualRoom": "أنشئ غرفة افتراضية",
        "deleteChannel": "حذف القناة",
        "deleteRoom": "حذف الغرفة",
        "deleteSpace": "حذف المساحة",
        "deleteVirtualRoom": "حذف الغرفة الافتراضية",
        "editYourMessage": "عَدِل رسالتك",
        "expand": "وسع",
        "goToGuide": "انتقل إلى دليل الإستخدام",
        "joinChannel": "انضم إلى القناة لإرسال الرسائل وتلقي الإشعارات",
        "join": "انضم",
        "joinChannelAction": "انضم إلى القناة",
        "joinRoom": "انضم إلى الغرفة",
        "joinVirtualRoom": "انضم لغرفة إفتراضية",
        "leaveGroup": "مغادرة المجموعة",
        "leaveChannel": "مغادرة القناة",
        "leaveAndDelete": "مغادرة و حذف",
        "leave": "مغادرة",
        "leaveSpace": "مغادرة المساحة",
        "muteNotifications": "كتم الإشعارات",
        "openInChats": "افتح في الدردشات",
        "openInTeam": "افتح في الفريق",
        "plan": "خطط",
        "removeMember": "إزالة العضو",
        "remove": "إزالة",
        "replyToSomeone": "الرد على",
        "replyToYourself": "الرد على نفسك",
        "saveToFiles": "حفظه في الملفات",
        "scrollToNewMessage": "انتقل إلى الرسالة الجديدة",
        "planMeeting": "التخطيط لاجتماع",
        "scrollToTheBottom": "انتقل إلى الأسفل",
        "start": "إبدأ",
        "startMeeting": "إبدأ إجتماع",
        "stop": "أنهي",
        "waitingModeratorToJoin": "ننتظر أن يتم قبولك من قبل المشرف"
    },
    "preview": {
        "close": {
            "tooltip": "إغلاق"
        },
        "actions": {
            "tooltip": {
                "download": "تنزيل"
            }
        }
    },
    "conversations": {
        "activeRooms": "الغرف النشطة",
        "activeVirtualRooms": "الغرف الافتراضية النشطة",
        "conversations": "المحادثات",
        "filterChatList": "تصفية قائمة الدردشات",
        "instantMeetings": "الاجتماعات الفورية",
        "meetingRooms": "غرف الاجتماعات",
        "noActiveChats": "لا توجد دردشات نشطة في الوقت الحالي. قم بإنشاء دردشة جديدة أو غير لتبويبة الدردشات.",
        "mockDisplayDescription": "اختر محادثة لبدء الدردشة",
        "mockDisplayTitle": "لنبقى على تواصل!",
        "noActiveInstantMeetings": "لا توجد اجتماعات فورية نشطة في الوقت الحالي. قم بإنشاء صفحة اجتماع فوري أو بدل لتبويبة الاجتماعات.",
        "noActiveMeetings": "لا توجد غرف نشطة في الوقت الحالي",
        "noActiveSpaces": "لا توجد مساحات نشطة في الوقت الحالي. قم بإنشاء مساحة جديدة أو بدل لتبويبة المساحات.",
        "noActiveRooms": "لا توجد غرف نشطة في الوقت الحالي",
        "noFilteredChats": "لا توجد دردشات تطابق هذه التصفية.",
        "personalRoom": "غرفة شخصية",
        "personalVirtualRoom": "غرفة افتراضية شخصية",
        "rooms": "الغرف",
        "virtualRooms": "الغرف الافتراضية",
        "scheduledMeetings": "الاجتماعات المجدولة",
        "spaceGeneralChannel": "العامه",
        "spaces": "المساحات",
        "waitingRoom": "غرفة الانتظار",
        "yourRoom": "غرفتك",
        "noFilteredSpaces": "لا توجد مسافات تطابق هذه التصفية.",
        "noFilteredVirtualRooms": "لا توجد غرف افتراضية أو اجتماعات مخططة تتوافق مع هذه التصفية",
        "noActiveVirtualRooms": "لا توجد غرف افتراضية نشطة في الوقت الحالي",
        "activeMeetingRooms": "غرف الاجتماعات النشطة",
        "chats": "الدردشات",
        "noFilteredInstantMeetings": "لا توجد اجتماعات فورية تطابق هذه التصفية.",
        "noFilteredMeetings": "لا توجد غرف أو اجتماعات مخططة تتوافق مع هذه التصفية",
        "noFilteredRooms": "لا توجد غرف أو اجتماعات مخططة تتوافق مع هذه التصفية"
    },
    "creation": {
        "attendeeAdded": "تمت إضافة الحضور إلى القائمة",
        "channel": {
            "mainDescription": "القنوات عبارة عن دردشات موضوعية محددة جيدًا يتم تضمينها في مساحة. يمكن لمشاركي المساحة الانضمام إلى القناة لمناقشة موضوعها بنشاط. يمكن للمشاركين مغادرة القناة دون مغادرة المساحة أيضًا.",
            "titleInputRequirements": "المسموح به 140 حرفًا، ويجب أن يكون العنوان فريدًا داخل مساحة الاستضافة",
            "topicInputExplanation": "يصف موضوع القناة",
            "setImageAndTitleDescription": "قم بتعيين صورة للتعرف بشكل أفضل على القناة داخل مساحة الاستضافة. يمكن أيضًا تعيين صورة القناة أو تغييرها في لوحة معلومات القناة.",
            "topicDescription": "نظرًا لأن القنوات عبارة عن دردشات تعتمد على الموضوع الذي تتم مناقشته، فمن المستحسن استخدام موضوع يصف الموضوع بشكل أفضل."
        },
        "chat": {
            "addParticipant": "اختر مُشاركًا لبدء الدردشة معه",
            "chatFilterDescription": "يمكنك إنشاء دردشة فقط من خلال النقر على المشارك الذي تريد التحدث معه",
            "description": "الدردشات هي محادثات فردية تساعدك على البقاء على اتصال مع جهات الاتصال الخاصة بك."
        },
        "emailReplicated": "البريد الإلكتروني الذي تم إدخاله مضاف مسبقاً",
        "group": {
            "addParticipantsDescription": "قم بدعوة المشاركين عن طريق كتابة أسمائهم أو عناوين بريدهم الإلكتروني. يجب عليك دعوة مشاركين آخرين على الأقل، وإلا يمكنك إنشاء دردشة.",
            "groupWithoutNameAddParticipant": "إضافة مشاركين إلى مجموعتك",
            "inputTopicDescriptionLabel": "يصف موضوع المجموعة",
            "setImageAndTopicDescription": "تعيين صورة تساعد المستخدمين على تحديد المجموعة من المجموعات الموجودة في القائمة.",
            "mainDescription": "يجب أن تضم المجموعات أكثر من مشاركين إثنين. تسمية المجموعة على أنها مفضلة لوصف موضوعها"
        },
        "instantMeeting": {
            "addAttendees": "إضافة حاضرين إلى اجتماعك الفوري",
            "addAttendeesInputExplanation": "يمكنك أيضا دعوة مستخدمين خارجيين فقط عن طريق كتابة عنوان بريدهم الإلكتروني.",
            "attendee": {
                "feedback": {
                    "neutral": "تحديد حاضر واحد أو أكثر",
                    "negative": "البريد الإلكتروني الذي تم إدخاله غير صحيح ، يرجى إدخال عنوان بريد إلكتروني صحيح"
                }
            },
            "description": "الاجتماعات الفورية عبارة عن مكالمات فيديو مصممة لتكون سريعة ولحظية، ولن يتم الاحتفاظ بأي أثر للدردشة وبمجرد انتهاء المكالمة، ستتوقف عن الوجود. يمكن إنشاء الاجتماعات الفورية بواسطة مستخدمي الفريق الاحترافي -Team Pro- ويمكن أيضًا للمستخدمين الخارجيين الانضمام إليها.",
            "addAttendeesDescription": "قم بدعوة الحاضرين عن طريق كتابة أسمائهم أو عنوان بريدهم الإلكتروني هنا.",
            "titleDescription": "امنح عنوانا مميزا للاجتماع الفوري، حتى يعرف الحاضرون الغرض من هذه المكالمة."
        },
        "limitOfParticipantReached": "لقد وصلت إلى الحد الأقصى للمشاركين الذي حدده المسؤول",
        "nameMax140Characters": "الحد الأقصى 140 حرفا",
        "nameNeeds2Letters": "الاسم يحتاج إلى حرفين على الأقل",
        "nameRequired": "الإسم مطلوب",
        "participants": {
            "feedback": {
                "neutral": "حدد مشاركين إثنين أو أكثر"
            }
        },
        "nameRequired-max140Characters-avoidReusingNames": "مطلوب. 140 حرفا كحد أقصى، تجنب إعادة استخدام الإسم.",
        "requiresOneMoreParticipant": "يتطلب مشاركا واحدا آخر على الأقل",
        "requiresTwoOthers": "يتطلب ما لا يقل عن 2 آخرين",
        "selectMoreParticipantsForInstantMeetings": "حدد مشاركا من القائمة أو اكتب العنوان لإضافة مستخدم خارجي",
        "selectOneOrMoreUsers": "تحديد مستخدم واحد أو أكثر",
        "space": {
            "spaceWithoutNameAddParticipant": "إضافة مشاركين إلى مساحتك",
            "titleDescription": "العنوان يحدد ماهي المساحة وبالتالي يجب أن يصف موضوعها.",
            "topicInputExplanation": "يصف موضوع المساحة",
            "addMembersDescription": "قم بدعوة الأشخاص عن طريق كتابة أسمائهم أو عناوين بريدهم الإلكتروني. يجب عليك دعوة شخصين آخرين على الأقل، وإلا فيمكنك إنشاء دردشة.",
            "mainDescription": "المساحات عبارة عن بيئات اتصال عامة تتضمن دردشات محددة تسمى القنوات، ولكل منها موضوعها الخاص. لإنشاء مساحة، تحتاج إلى دعوة مشاركين اثنين على الأقل. يمكن إضافة القنوات مباشرة من لوحة معلومات المساحة.",
            "topicDescription": "نظرا لأن المساحات عبارة عن دردشات مبنيةٌ على الموضوع الذي تمت مناقشته ، يوصى بعنوان يصف الموضوع بشكل أفضل."
        },
        "startTypingToPick": "ابدأ بالكتابة لاختيار عنوان",
        "titleInputRequirements": "140 حرفا مسموحا به ، يجب أن يكون العنوان فريدا من نوعه",
        "topicMax255Characters": "الحد الأقصى 255 حرفا",
        "topicOptional": "اختياري. يصف الموضوع",
        "topicNeeds2Letters": "الموضوع اختياري. الحد الأدنى حرفين",
        "typeToFilter": "اكتب لتصفية القائمة",
        "typeWithNameAddParticipant": "إضافة مشاركين إلى",
        "youCanInviteOther": "يمكنك دعوة {{limit}} مشارك/مشاركين آخرين"
    },
    "enterTheRoom": "ادخل إلى الغرفة",
    "enterTheVirtualRoom": "ادخل إلى الغرفة الافتراضية",
    "errorPage": {
        "description": "تحقق من الرابط الخاص بك ، قد يكون الرابط خطا",
        "errorCode": "رمز الخطأ 404",
        "title": "عذرا، لم نتمكن من العثور على تلك الغرفة"
    },
    "external": {
        "appStoreLabel": "متجر التطبيقات",
        "doYouHaveTheAppTeam": "هل لديك تطبيق دردشات زيكستراس -Zextras Chats-؟",
        "roomIsEmpty": "هذه الغرفة فارغة",
        "unsupported": {
            "browser": "متصفحك غير مدعوم",
            "device": "جهازك غير مدعوم"
        },
        "youAreEnteringVirtualRoom": "أنت على وشك الدخول إلى الغرفة الافتراضية",
        "nobodyInTheRoom": "يبدو أنه لا يوجد أحد في هذه الغرفة",
        "nobodyInTheVirtualRoom": "يبدو أنه لا يوجد أحد في هذه الغرفة الافتراضية",
        "orLabel": "أو",
        "login": {
            "externalLoginDescription": "إذا كنت تنتمي إلى هذا المجال ، إعادة توجيهك إلى صفحة مساحة العمل المعتادة. إذا كنت مستخدما خارجيا ، إعادة توجيهك إلى صفحة مخصصة."
        },
        "doYouHaveTheApp": "هل تملك تطبيق الدردشات ؟",
        "doYouHaveTheAppChats": "هل لديك تطبيق دردشات كربونيو -Carbonio Chats-؟",
        "downloadAppLabel": "قم بتنزيل التطبيق للانضمام إلى الاجتماع",
        "enter": "إنظم!",
        "playStoreLabel": "جوجل بلاي",
        "virtualRoomIsEmpty": "هذه الغرفة الافتراضية فارغة",
        "waitingRoom": {
            "accessDenied": "الوصول مرفوض",
            "moderatorRefusedAccessToRoom": "رفض أحد المنسقين دخولك إلى هذه القاعة",
            "userLeftLookForwardToSee": "نتطلع إلى رؤيتك مرة أخرى",
            "userLeftReturnToWaitingRoom": "يمكنك العودة إلى غرفة الانتظار في أي وقت من رابط الغرفة",
            "userLeftWaitingRoom": "لقد غادرت غرفة الانتظار"
        },
        "youAreEnteringMeeting": "أنت على وشك دخول الغرفة"
    },
    "feedback": {
        "appVersionCopied": "تم نسخ إصدار التطبيق",
        "connecting": "توصيل…",
        "notificationsMutedForThisChat": "الإشعارات كُتمت لهذه الدردشة",
        "offline": "يبدو أنها مشكلة في الاتصال بالخادم",
        "online": "عدنا!",
        "resetPersonalVirtualRoomLinkSuccess": "تمت إعادة تعيين رابط الغرفة الافتراضية الشخصية",
        "resetPersonalRoomLinkSuccess": "تمت إعادة تعيين رابط الغرفة الشخصية",
        "saveAttachmentError": "يبدو أن هناك مشكلة عند الحفظ ، يرجى المحاولة مرة أخرى",
        "saveAttachmentSuccessfull": "حُفظ المرفق في المجلد المحدد",
        "tryAReconnectionIn": "إعادة الاتصال في {{seconds}}",
        "historyClearedSuccessfully": "تم مسح السجل بنجاح!",
        "notificationsActivatedForThisChat": "الإشعارات نُشطت لهذه الدردشة",
        "retryConnection": "إعادة محاولة الاتصال",
        "roomLinkCopied": "تم نسخ رابط الغرفة",
        "linkCopied": "تم نسخ الرابط",
        "uploadConversationPicturesFailed": "فشل تحميل صورة المحادثة",
        "virtualRoomLinkCopied": "تم نسخ رابط الغرفة الافتراضية"
    },
    "message": {
        "service": {
            "member": {
                "created": {
                    "channel": "لقد أنشأ {{member_name}} القناة",
                    "group": "لقد أنشأ {{member_name}} المجموعة",
                    "single": "لقد أنشأ {{member_name}} الدردشة",
                    "space": "لقد أنشأ {{member_name}} المساحة"
                },
                "changed": {
                    "name": {
                        "space": "{{member_name}} غير إسم المساحة لـ{{name}}",
                        "channel": "{{member_name}} غير إسم القناة لـ{{name}}"
                    },
                    "picture": {
                        "space": "{{member_name}} غير صورة المساحة",
                        "channel": "{{member_name}} غير صورة القناة",
                        "group": "{{member_name}} غير صورة المجموعة"
                    },
                    "topic": {
                        "group": "{{member_name}} غير موضوع المجموعة في {{topic}}",
                        "space": "{{member_name}} غير موضوع المساحة في {{topic}}",
                        "channel": "{{member_name}} غير موضوع القناة في {{topic}}"
                    }
                },
                "deleted": {
                    "channel": "{{member_name}} حذف القناة",
                    "space": "{{member_name}} حذف المساحة",
                    "instantMeeting": "{{member_name}} حذف الاجتماع الفوري"
                },
                "join": {
                    "channel": "انضم {{member_name}} إلى القناة",
                    "conversation": "انضم {{member_name}} إلى الدردشة"
                },
                "kicked": {
                    "chat": "{{member_name}} أُزيل من الدردشة من قبل {{kicked_by}}",
                    "space": "{{member_name}} أُزيل من المساحة من قبل {{kicked_by}}",
                    "channel": "{{member_name}} أُزيل من القناة من قبل {{kicked_by}}",
                    "group": "{{member_name}} أُزيل من المجموعة من قبل {{kicked_by}}"
                },
                "left": {
                    "group": "لقد غادر {{member_name}} المجموعة",
                    "chat": "{{member_name}} غادر الدردشة",
                    "channel": "لقد غادر {{member_name}} القناة",
                    "space": "لقد غادر {{member_name}} المساحة"
                },
                "you": {
                    "invited": "لقد قمت بدعوة {{member_name}}",
                    "kicked": {
                        "group": "لقد قمت بإزالة {{member_name}} من المجموعة",
                        "channel": "لقد قمت بإزالة {{member_name}} من القناة",
                        "space": "لقد قمت بإزالة {{member_name}} من المساحة"
                    }
                },
                "invited": "{{member_name}} دُعي من قبل {{invited_by}}"
            },
            "conversationCreated": "تم إنشاء الدردشة",
            "you": {
                "created": {
                    "channel": "لقد قمت بإنشاء القناة",
                    "group": "لقد قمت بإنشاء المجموعة",
                    "single": "لقد قمت بإنشاء الدردشة",
                    "space": "لقد قمت بإنشاء المساحة"
                },
                "changed": {
                    "picture": {
                        "channel": "لقد قمت بتغيير صورة القناة",
                        "group": "لقد قمت بتغيير صورة المجموعة",
                        "space": "لقد قمت بتغيير اسم المساحة"
                    },
                    "name": {
                        "space": "لقد قمت بتغيير اسم المساحة في {{name}}",
                        "channel": "لقد قمت بتغيير اسم القناة في {{name}}"
                    },
                    "topic": {
                        "channel": "لقد قمت بتغيير موضوع القناة في {{topic}}",
                        "group": "لقد قمت بتغيير موضوع المجموعة في {{topic}}",
                        "space": "لقد قمت بتغيير موضوع المساحة في {{topic}}"
                    }
                },
                "deleted": {
                    "channel": "لقد قمت بحذف القناة",
                    "instantMeeting": "لقد قمت بحذف الاجتماع الفوري",
                    "space": "لقد قمت بحذف المساحة"
                },
                "join": {
                    "group": "لقد انضممت إلى المجموعة",
                    "instantMeeting": "لقد انضممت إلى الاجتماع الفوري",
                    "space": "لقد انضممت إلى المساحة",
                    "userRoom": "لقد انضممت إلى الغرفة",
                    "channel": "لقد انضممت إلى القناة"
                },
                "kicked": {
                    "channel": "لقد تم إزالتك من القناة بواسطة {{kicked_by}}",
                    "group": "لقد تم إزالتك من المجموعة بواسطة {{kicked_by}}",
                    "space": "لقد تم إزالتك من المساحة بواسطة {{kicked_by}}"
                },
                "left": {
                    "group": "لقد غادرت المجموعة",
                    "space": "لقد غادرت المساحة",
                    "channel": "لقد غادرت القناة"
                },
                "invited": "لقد تمت دعوتك بواسطة {{invited_by}}"
            },
            "notificationsMutedForThisChat": "اﻹشعارات كُتمت لهذه الدردشة",
            "notificationsActivatedForThisChat": "اﻹشعارات فُعلت لهذه الدردشة",
            "meeting": {
                "ended": "انتهى الاجتماع",
                "endedAtTime": "انتهى الاجتماع في",
                "startedAtTime": "بدأ الاجتماع في"
            },
            "newMeeting": "مكالمة واردة من:"
        },
        "deletedMessage": "الرسالة محذوفة",
        "yesterday": "أمس",
        "edited": "محررةٌ",
        "forwarded": "معاد توجيهها",
        "now": "الآن",
        "readBy": "قُرأت من قبل"
    },
    "modal": {
        "instantMeeting": {
            "create": "إنشاء اجتماع فوري جديد",
            "closedInstantMeeting": "تم إغلاق الاجتماع الفوري",
            "continue": "متابعة الاجتماع الفوري القديم",
            "endCallByOwner": "لقد قرر مالك الاجتماع الفوري على إنهاء المكالمة، نأمل أن تكون قد استمتعت بتجربة الاجتماع الفوري",
            "instantMeetingAlreadyRunningText": "إن إنشاء اجتماع جديد سيؤدي إلى استبدال الاجتماع القديم وسيفقد الحاضرون الاتصال، فماذا تريد أن تفعل؟",
            "instantMeetingAlreadyRunningTitle": "اجتماع فوري قيد التشغيل"
        },
        "addModeratorDescription": "حدد مستخدمًا واحدًا أو أكثر لترقيتهم إلى مشرفين على هذه الغرفة",
        "confirm": {
            "areYouSure": "هل أنت متأكد؟",
            "deleteRoom": "هل أنت متأكد من حذف الغرفة؟",
            "leaveChannel": "هل أنت متأكد من مغادرة القناة؟",
            "leaveGroup": "هل أنت متأكد من أنك تريد مغادرة المجموعة؟",
            "leaveSpace": "هل أنت متأكد من مغادرة المساحة؟",
            "deleteVirtualRoom": "هل أنت متأكد أنك تريد حذف الغرفة الافتراضية؟",
            "leaveAndDeleteConversation": "هل أنت متأكد أنك تريد مغادرة وحذف {{conversationName}}؟",
            "clearHistory": "سيتم مسح سجل الدردشة الخاص بك بشكل دائم. لن يتم حذف سجل الدردشة الخاص بالمشاركين الآخرين. هذا الإجراء لا رجعة فيه.",
            "deleteChannel": "هل أنت متأكد من حذف هذه القناة؟",
            "deleteSpace": "هل أنت متأكد من حذف هذه المساحة؟",
            "removeMember": "هل أنت متأكد أنك تريد إزالة هذا العضو؟"
        },
        "deleteMessageDescription": "عند حذف رسالة، لن تكون مرئية لك ولجميع المستلمين الآخرين بعد الآن",
        "forwardModal": {
            "forwardedMessageFrom": "رسالة معاد توجيهها من",
            "selectOneOrMoreConversations": "حدد محادثة واحدة أو أكثر",
            "spaceAndChannels": "المساحة والقنوات",
            "typeToFilterTheList": "اكتب لتصفية القائمة"
        },
        "moderatorCannotLeaveGroupDescription": "أنت المشرف الوحيد على {{conversationName}}، يرجى ترقية شخص آخر قبل مغادرة المجموعة.",
        "moderatorCannotLeaveGroupTitle": "انتظر، هناك حاجة إلى مشرف جديد",
        "moderatorMeetingDescription": "أنت من سيدير هذه الغرفة. يمكنك إضافة مشرفين إضافيين وسيكون لديهم نفس الصلاحيات التي لديك.",
        "moderatorVirtualRoomDescription": "أنت من سيدير هذه الغرفة الافتراضية. يمكنك إضافة مشرفين إضافيين وسيكون لديهم نفس الصلاحيات التي لديك.",
        "moderatorRoomDescription": "أنت من سيدير هذه الغرفة. يمكنك إضافة مشرفين إضافيين وسيكون لديهم نفس الصلاحيات التي لديك.",
        "news": "الأخبار",
        "notShowAgain": "لا تظهره مرة أخرى",
        "planMeetingDescription": "يساعد اسم الغرفة الحضور على معرفة موضوع المناقشة في الغرفة.",
        "planVirtualRoomDescription": "قم بإعطاء هذه الغرفة الافتراضية اسمًا يمكن التعرف عليه حتى يتمكن الحاضرون من معرفة ما يتوقعون الاجتماع بشأنه.",
        "planRoomDescription": "قم بإعطاء هذه الغرفة اسمًا يمكن التعرف عليه حتى يتمكن الحاضرون من معرفة ما يتوقعون الاجتماع بشأنه.",
        "selectFolder": "إختر مجلد",
        "stopMeetingRec": {
            "locationWhereToSaveRecording": "سيتم حفظ التسجيل في \"/{{folderName}}\".",
            "recordingName": "اسم التسجيل",
            "stopMeetingTitle": "إيقاف تسجيل الاجتماع",
            "stopRecording": "سيتم إيقاف التسجيل. يمكنك بدء تسجيل جديد في أي وقت أثناء هذا الاجتماع.",
            "stopRecordingTitle": "إيقاف التسجيل",
            "stopRecordingDescription": "سوف تقوم بإيقاف التسجيل. يمكنك بدء تسجيل جديد في أي وقت."
        },
        "clearHistoryDescription": "هذه المحادثة فارغة الآن، وتم نقلها إلى أسفل قائمة المحادثات ﻹظهار المحادثات النشطة.",
        "roomsFunctionalitiesChangelogDescription": "لقد أجرينا تغييرات مهمة على وظائف الاجتماعات. اقرأ مقدمة الغرف لمعرفة المزيد!",
        "teamNews": "اخبار الفريق",
        "userJoinedWaitingRoom": "يبدو أن هناك شخص في غرفة الانتظار"
    },
    "appVersion": "نسخة التطبيق",
    "attachments": {
        "addFromLocal": "أضف من جهازك",
        "attachLinkFiles": "إرفاق رابط عام من الملفات",
        "attachLinkFromFiles": "إرفاق رابط من الملفات",
        "share": "مشاركة الرابط العام",
        "shareLink": "شارك الرابط"
    },
    "button": {
        "cancel": "ألغِ",
        "no": "لا",
        "ok": "حسناً",
        "save": "حفظ",
        "undo": "التراجع",
        "yes": "نعم"
    },
    "conversation": {
        "channelInfo": "معلومات القناة",
        "contactInfo": "معلومات الاتصال",
        "fileUploadDescription": "وصف الملف",
        "groupInfo": "معلومات المجموعة",
        "info": "المعلومات",
        "instantInfo": "معلومات الاجتماع الفوري",
        "name": "الإسم",
        "nameRoom": "{{conversationTitle}}غرفة {{conversationTitle}}",
        "nameVirtualRoom": "الغرفة الافتراضية لـ {{conversationTitle}}",
        "newMessages": "رسائل جديدة",
        "roomInfo": "معلومات الغرفة",
        "roomLink": "رابط الغرفة",
        "roomLinkDescription": "انسخ هذا الرابط وشاركه ليتمكن الآخرون من الوصول إلى هذه الغرفة.",
        "roomName": "اسم الغرفة",
        "spaceInfo": "معلومات المساحة",
        "speakersCorner": "المستخدمون في غرفة الاجتماعات",
        "title": "العنوان",
        "topic": "المحادثة",
        "virtualRoomInfo": "معلومات الغرفة الافتراضية",
        "virtualRoomLink": "رابط الغرفة الافتراضية",
        "virtualRoomLinkDescription": "انسخ هذا الرابط وشاركه ليتمكن الآخرون من الوصول إلى هذه الغرفة الافتراضية.",
        "virtualRoomName": "اسم الغرفة الافتراضية"
    },
    "tooltip": {
        "disabledCreateButton": "تحقق من مدخلاتك للتأكد من عدم وجود أخطاء",
        "switchToConversation": "بدل للمحادثة",
        "goToPrivateChat": "انتقل إلى الدردشة الخاصة",
        "openMinichat": "إفتح الدردشة المصغرة",
        "copyRoomLinkTooltip": "انسخ هذا الرابط لمشاركة الغرفة",
        "copyRoomLink": "نسخ هذا الرابط لمشاركة الغرفة",
        "copyUserRoomTooltip": "انسخ هذا الرابط وشاركه لتزويد الآخرين بإمكانية الوصول إلى غرفتك الشخصية",
        "copyUserRoom": "نسخ رابط غرفتك الشخصية",
        "copyUserVirtualRoomTooltip": "انسخ هذا الرابط وشاركه لتزويد الآخرين بإمكانية الوصول إلى غرفتك الافتراضية الشخصية",
        "copyVirtualRoomLinkTooltip": "انسخ هذا الرابط لمشاركة الغرفة الافتراضية",
        "editDescription": "تعديل الوصف",
        "editInfo": "تعديل المعلومات",
        "enterYourVirtualRoomTooltip": "أدخل غرفتك الافتراضية الشخصية",
        "errorUploadingAvatarPicture": "حدث خطأ أثناء تحميل الصورة الرمزية الجديدة. يرجى إعادة المحاولة",
        "planMeeting": "التخطيط لاجتماع",
        "promoteModerator": "الترقية إلى مشرف",
        "removeMember": "إزالة العضو",
        "sendMessage": "أرسل رسالة",
        "switchToInfoPanel": "التبديل إلى لوحة المعلومات",
        "cancelFilter": "إلغاء التصفية",
        "chooseFile": "اختر ملف",
        "close": "أغلق",
        "addFile": "أضف ملف",
        "rejectQueuedMember": "رفض المستخدم",
        "acceptQueuedMember": "السماح للمستخدم بالدخول",
        "chooseRoom": "اختر غرفة افتراضية",
        "closeSearch": "أغلق البحث",
        "collapseChannel": "طي القنوات",
        "downgradeModerator": "تخفيض مستوى المشرف",
        "enterMeetingRoom": "ادخل إلى غرفة الاجتماعات",
        "enterYourRoom": "أدخل غرفتك الشخصية",
        "enterYourRoomTooltip": "أدخل غرفتك الشخصية",
        "errorRemovingAvatarPicture": "حدث خطأ أثناء إزالة الصورة الرمزية. يرجى إعادة المحاولة",
        "errorUpdatingAvatarStatus": "حدث خطأ أثناء حالة الإعدادات. يرجى إعادة المحاولة",
        "inviteToPersonalRoom": "دعوة إلى غرفتك الشخصية",
        "messageComposer": "مؤلف الرسالة",
        "removeFile": "إزالة الملف",
        "searchForParticipant": "البحث عن المشارك",
        "selectEmoji": "إختر الرمز التعبيري -إيموجي-",
        "sendFile": "أرسل الملف",
        "showChannels": "أظهر القنوات"
    },
    "general": {
        "teamProductName": "الفريق",
        "browserNotSupported": "إصدار المتصفح الخاص بك غير مدعوم. يوصى بشدة بتحديث المتصفح للاستفادة من جميع الميزات!",
        "goToTeam": "إنتقل للفريق"
    },
    "meeting": {
        "attendeesComing": "المشاركون قادمون",
        "blurMyBackground": "طَمِّس خلفيتي",
        "defaultViewModeDedicatedLabel": "سيعمل \"الوضع المخصص\" على إعادة توجيهك إلى تبويبة منفصلة في متصفحك للاستمتاع بتجربة الاجتماع في أفضل حالاتها.",
        "defaultViewModeDedicatedModeLabel": "الوضع المخصص",
        "defaultViewModeDedicatedModeLabelVirtualRoom": "الوضع المخصص",
        "genericErrorMeeting": "يبدو أن هناك مشكلة في هذا الاجتماع، اتصل بمسؤول النظام لديك.",
        "interactions": {
            "audioDisabled": "الصوت معطل",
            "audioEnabled": "الصوت مُمَكنٌ",
            "cameraDisabled": "الكاميرا معطلةٌ",
            "cameraEnabled": "الكاميرا ممكنةٌ",
            "cinemaView": "العرض السينمائي",
            "closeCall": "إغلاق المكالمة",
            "disableAudio": "تعطيل الصوت",
            "disableVideo": "تعطيل الفيديو",
            "enableAudio": "تمكين الصوت",
            "enableFullScreen": "الشاشة الكاملة",
            "enableScreenSharing": "تمكين مشاركة الشاشة",
            "gridView": "العرض الشبكي",
            "hangOff": "أغلق اﻹجتماع",
            "micTesting": "ستسمع صوتك على المخرج الافتراضي، مما يسمح لك باختبار جودة مدخل الصوت بالإضافة إلى المخرج المحدد للاجتماع",
            "muteUser": "كتم",
            "muteUserForAllTitle": "كتم الصوت للجميع",
            "mutedByModerators": "لقد تم كتم صوتك بواسطة أحد المشرفين، قم بإلغاء كتم صوتك لتتمكن من التحدث",
            "mutedByOthers": "لقد تم كتم صوتك",
            "pinVideo": "تثبيت الفيديو",
            "playMic": "إبدأ اختبار الميكروفون",
            "playMyVoice": "إستمع لصوتي",
            "showChat": "عرض الدردشة",
            "showParticipants": "عرض المشاركين",
            "status": {
                "cameraMicOff": "الكاميرا والميكروفون الخاصين بك معطلين",
                "cameraOff": "الكاميرا الخاصة بك معطلة"
            },
            "stopMic": "إيقاف اختبار الميكروفون",
            "muteUserForAllDescription": "من خلال كتم صوت المستخدم، لن يسمعه جميع المشاركين بعد الآن. فقط المستخدم الذي تم كتم صوته يمكنه إلغاء كتم صوته بنفسه. هل تريد المتابعة؟",
            "disableFullScreen": "الخروج من الشاشة الكاملة",
            "disableScreensharing": "تعطيل مشاركة الشاشة",
            "enableVideo": "تمكين الفيديو",
            "hideChat": "إخفاء الدردشة",
            "hideParticipants": "إخفاء المشاركين",
            "shortCutLabel": "(C)",
            "stopMyVoice": "عطل صوتي",
            "unpinVideo": "إلغاء تثبيت الفيديو"
        },
        "noEffect": "لا تأثيرات",
        "resetMeetingUrlModalDescription": "هل أنت متأكد من إعادة تعيين الرابط للإجتماع \"{{conversationName}}\" المخطط له؟",
        "setVirtualBackground": "تعيين الخلفية الافتراضية",
        "startModal": {
            "description": "كيف تريد الدخول إلى الاجتماع؟",
            "descriptionMyPersonalRoom": "كيف تريد الدخول إلى غرفتك الشخصية؟",
            "descriptionMyPersonalVirtualRoom": "كيف تريد الدخول إلى غرفتك الإفتراضية الشخصية؟",
            "descriptionPersonalRoom": "كيف تريد الدخول إلى غرفة {{meeting Title}} الشخصية؟",
            "descriptionPersonalVirtualRoom": "كيف تريد الدخول إلى الغرفة الافتراضية الشخصية {{meetingTitle}}؟",
            "noVideoAndAudio": "الكاميرا معطلة والميكروفون مفعل",
            "videoAndNoAudio": "الكاميرا مفعلة والميكروفون معطل",
            "noVideoAndNoAudio": "الكاميرا معطلة والميكروفون معطل",
            "videoAndAudio": "الكاميرا مفعلة والميكروفون مفعل",
            "descriptionVirtualRoom": "كيف تريد الدخول إلى {{meetingTitle}}؟",
            "enter": "إدخل"
        },
        "wereToFindRec": "سيتم حفظ التسجيل في مساحة الملفات الخاصة بالمشرف الذي أوقف التسجيل.",
        "successSaveMeetingRecording": "ستجل {{registrationName}} في {{folderName}} بمجرد توفره",
        "thisMeetingIsBeingRecorded": "هذا اﻹجتماع يتم تسجيله",
        "wereToFindRecording": "سيتم حفظ التسجيل في خادم الفيديو الرئيسي، اتصل بمسؤول النظام لديك لمزيد من التفاصيل.",
        "defaultViewModeDefaultLabelVirtualRoom": "عند تحديد \"الوضع الافتراضي\" ، ستبدأ الغرفة الافتراضية في البيئة الداخلية الحالية.",
        "defaultViewModeDefaultModeLabel": "الوضع الافتراضي",
        "defaultViewModeSaveLabel": "حفظ الخيار",
        "defaultViewModeSecondaryDescriptionLabel": "سيتم حفظ هذا الخيار في إعداداتك ويمكن تحديثه في أي وقت تريده.",
        "defaultViewModeTitleModal": "خيارات بيئة الاجتماعات",
        "errorMeetingRecording": "لا يمكن البدء بالتسجيل، يرجى الاتصال بمسؤول النظام الخاص بك.",
        "errorMeetingSavingRecording": "لا يمكن إيقاف التسجيل، يرجى المحاولة مرة أخرى",
        "defaultViewModeDefaultLabel": "عند تحديد \"الوضع الافتراضي\"، سيبدأ الاجتماع في البيئة الداخلية الحالية.",
        "defaultViewModeTitleModalVirtualRoom": "خيارات بيئة الغرف الافتراضية",
        "defaultViewModeDedicatedLabelVirtualRoom": "سيعمل \"الوضع المخصص\" على إعادة توجيهك إلى تبويبة منفصلة في متصفحك للاستمتاع بتجربة الغرفة الافتراضية في أفضل حالاتها.",
        "defaultViewModeDedicatedModeLabelVRoom": "الوضع المخصص",
        "recordedByMe": "لقد بدأت التسجيل",
        "recordedByOther": "بدأ {{username}} تسجيل الاجتماع",
        "recording": "تسجيل"
    },
    "label": {
        "app_name": "الدردشات"
    },
    "notification": {
        "waiting": {
            "descriptionWaitingLabel": "أنت تنتظر أن يتم قبولك من قبل مشرف {{conversationName}}",
            "descriptionAcceptedLabel": "لقد تم قبولك من قبل المشرف لـ{{conversationName}}",
            "notificationAcceptedByModerator": "لقد تم قبولك من قبل المشرف",
            "notificationJoinTheRoom": "انضم إلى الغرفة للمشاركة في الاجتماع",
            "notificationJoinTheVirtualRoom": "انضم إلى الغرفة الافتراضية للمشاركة في الاجتماع",
            "userIsWaiting": "المستخدم الجديد ينتظر الدخول",
            "userJoinedWaitingRoom": "يبدو أن هناك شخص ما في غرفة الانتظار"
        },
        "startMeetingRecording": "لقد بدأ تسجيل اجتماع {{conversationName}}",
        "dismiss": "أبعد",
        "answer": "أجب",
        "incomingCall": "مكالمة واردة من:",
        "invitationToPersonalRoom": "دعوة إلى الغرفة الشخصية من:",
        "invitationToPersonalVirtualRoom": "دعوة إلى الغرفة الافتراضية الشخصية من:",
        "meeting": {
            "ended": "انتهى الاجتماع"
        }
    },
    "organizeYourMeeting": "قم بتنظيم اجتماعاتك الخاصة أو انضم إلى غرف زملائك",
    "organizeYourVirtualMeeting": "قم بتنظيم اجتماعاتك الخاصة أو انضم إلى الغرف الافتراضية لزملائك",
    "people": {
        "manyMembers": "{{membersCount}} عضوًا",
        "me": "أنا",
        "oneParticipant": "مشارك واحد",
        "otherParticipants": "{{numberParticipants}} مشاركين آخرين",
        "participants": "المشاركون",
        "whoYoureLookinkFor": "تبحث عن من؟",
        "you": "أنت"
    },
    "room": "الغرفة الافتراضية",
    "settings": {
        "meeting": {
            "enableEchoCancellation": "إلغاء الصدى",
            "enableMicrophone": "مكن الميكروفون",
            "enableCamera": "مَكِن الكاميرا",
            "enableNoiseSuppression": "قمع الضوضاء",
            "description": "اضبط إعدادات الصوت والفيديو الخاصة بك للدخول إلى الاجتماعات. يمكنك دائمًا تخصيص إعداداتك قبل الدخول إلى أي اجتماع.",
            "descriptionRoom": "اضبط إعدادات الصوت والفيديو للدخول إلى الغرفة. يمكنك دائمًا تخصيص إعداداتك قبل الدخول إلى كل غرفة.",
            "descriptionVirtualRoom": "اضبط إعدادات الصوت والفيديو للدخول إلى الغرفة الافتراضية. يمكنك دائمًا تخصيص إعداداتك قبل الدخول إلى كل غرفة افتراضية.",
            "meetings": "الاجتماعات",
            "personalRoomOptionsTitleModal": "إعادة تعيين رابط الغرفة الشخصية",
            "personalRoomResetButton": "رابط إعادة تعيين الغرفة الشخصية",
            "personalRoomResetDescription": "عند إعادة تعيين رابط الغرفة الشخصية ، لن تعمل جميع روابط الوصول التي تم تقديمها سابقاً.",
            "personalVirtualRoomResetDescription": "عند تعيين رابط الغرفة الافتراضية الشخصية ، لن تعمل جميع روابط الوصول التي تم تقديمها سابقا.",
            "virtualRooms": "الغرف الافتراضية",
            "voiceProcessing": "معالجة الصوت",
            "voiceProcessingDescription": "‮ستسمع صوتك من المخرج الافتراضي ، مما يسمح لنفسك باختبار جودة مدخلاتك بالإضافة إلى المخرجات المحددة للاجتماع",
            "personalVirtualRoomOptionsTitleModal": "إعادة تعيين رابط الغرفة الافتراضية الشخصية",
            "personalVirtualRoomResetButton": "إعادة تعيين رابط الغرفة الافتراضية الشخصية"
        },
        "modal": {
            "title": "إعدادات الدردشات",
            "description": "هنا يمكنك تعيين إعدادات جميع الدردشات المخصصة للاستمتاع بتجربة دردشة مخصصة كاملة!"
        },
        "notification": {
            "title": {
                "openMinichatForSingle": "افتح عندما تصل رسالة واحدة جديدة",
                "openMinichatForSpace": "افتح عندما تصل رسالة مساحة جديدة",
                "openMinichat": "افتح عندما تصل رسالة جديدة",
                "openMinichatForGroup": "افتح عندما تصل رسالة جماعية جديدة",
                "notifications": "اﻹشعارات"
            },
            "openMinichatDescription": "قم بإعداد طريقة فتح الدردشات الصغيرة الخاصة بك",
            "desktop": "إشعارات سطح المكتب"
        },
        "notifications": {
            "description": "قم بتعيين الإعدادات لكل نوع من الإشعارات في الدردشات."
        },
        "profile": {
            "chooseAProfilePic": "اختر الصورة التعريفية ، سيتم توسيط الصورة تلقائيا.",
            "errorGenericResponse": "حدث خطأ ما. يرجى إعادة المحاولة",
            "maximumDimension": "البعد الأعلى: 256 كيلو بايت.",
            "reset": "اعاده التعيين",
            "restore": "استعاده",
            "statusOptionalDescription": "اختياري. دع الآخرين يعرفون ما الذي تفكر فيه. أقصى طول: 256 حرفا",
            "title": "ملف التعريف",
            "update": "تحديث"
        },
        "recordingMeeting": {
            "descriptionWhereToSaveRegistration": "قم بتعيين مجلد حفظ تسجيلات الاجتماعات.",
            "destinationFolder": "مجلد الوجهة",
            "recording": "التسجيلات"
        },
        "resetPersonalRoomLinkSuccess": "تم إعادة تعيين رابط الغرفة الشخصية",
        "title": "إعدادات"
    },
    "organizeYourVMeeting": "قم بتنظيم اجتماعاتك الخاصة أو انضم إلى الغرف الافتراضية لزملائك",
    "noRoomSelected": "لم يتم تحديد غرفة افتراضية",
    "personalRoomLabel": "الغرفة الشخصية لـ {{userName}}",
    "personalVirtualRoomLabel": "الغرفة الافتراضية الشخصية لـ {{userName}}",
    "status": {
        "areWriting": "يكتب…",
        "offline": "غير متصل",
        "externalGuest": "ضيف خارجي",
        "internalGuest": "ضيف داخلي",
        "isWriting": "يكتب…",
        "lastSeen": "آخر ظهور {{lastSeen}}",
        "online": "متصل",
        "userStatus": "الحالة",
        "waitingToEnter": "في انتظار الدخول"
    },
    "tryLater": "حاول لاحقا",
    "typeYourEmail": "اكتب بريدك الإلكتروني",
    "virtualRoom": "الغرفة الافتراضية",
    "thanksForParticipating": "شكرا على المشاركة"
}
